io4it-0.0.0.12.10-py3.11-nspkg.pth
orangecontrib/IO4IT/__init__.py
orangecontrib/IO4IT/ocr_function/__init__.py
orangecontrib/IO4IT/ocr_function/word_converter.py
orangecontrib/IO4IT/widgets/OWMarkdownizer.py
orangecontrib/IO4IT/widgets/OWPathPropagator.py
orangecontrib/IO4IT/widgets/OWS3Uploader.py
orangecontrib/IO4IT/widgets/OWS3downloader.py
orangecontrib/IO4IT/widgets/OWS3list.py
orangecontrib/IO4IT/widgets/OWSpeechToText.py
orangecontrib/IO4IT/widgets/OWwordpdf2docx.py
orangecontrib/IO4IT/widgets/__init__.py
orangecontrib/IO4IT/widgets/designer/ow_in_or_out_path.ui
orangecontrib/IO4IT/widgets/designer/owspeechtotext.ui
orangecontrib/IO4IT/widgets/designer/wordpdf2docx.ui
orangecontrib/IO4IT/widgets/icons/category.svg
orangecontrib/IO4IT/widgets/icons/download.png
orangecontrib/IO4IT/widgets/icons/in_or_out.png
orangecontrib/IO4IT/widgets/icons/list_aws.png
orangecontrib/IO4IT/widgets/icons/md.png
orangecontrib/IO4IT/widgets/icons/speech_to_text.png
orangecontrib/IO4IT/widgets/icons/upload.png
orangecontrib/IO4IT/widgets/icons/wordpdf2docx.png
io4it-0.0.0.12.10.dist-info/License.txt
io4it-0.0.0.12.10.dist-info/METADATA
io4it-0.0.0.12.10.dist-info/WHEEL
io4it-0.0.0.12.10.dist-info/entry_points.txt
io4it-0.0.0.12.10.dist-info/namespace_packages.txt
io4it-0.0.0.12.10.dist-info/top_level.txt
io4it-0.0.0.12.10.dist-info/RECORD
