Metadata-Version: 2.1
Name: io4it
Version: 0.0.0.12.10
Home-page: 
Author: 
Author-email: 
Keywords: orange3 add-on
License-File: License.txt
Requires-Dist: boto3
Requires-Dist: docling
Requires-Dist: docling-core
Requires-Dist: speechbrain
Requires-Dist: whisper
Requires-Dist: whisper-openai
Requires-Dist: pyannote.audio
Requires-Dist: pyannote.core
Requires-Dist: wave
Requires-Dist: scikit-learn
Provides-Extra: cuda
Requires-Dist: torch==2.6.0+cu126; extra == "cuda"
Requires-Dist: torchvision==0.17.2+cu126; extra == "cuda"
Requires-Dist: torchaudio==2.6.0+cu126; extra == "cuda"
